odoo/addons/fastapi_auth_partner/README.rst
odoo/addons/fastapi_auth_partner/__init__.py
odoo/addons/fastapi_auth_partner/__manifest__.py
odoo/addons/fastapi_auth_partner/dependencies.py
odoo/addons/fastapi_auth_partner/schemas.py
odoo/addons/fastapi_auth_partner/demo/fastapi_endpoint_demo.xml
odoo/addons/fastapi_auth_partner/i18n/fastapi_auth_partner.pot
odoo/addons/fastapi_auth_partner/i18n/it.po
odoo/addons/fastapi_auth_partner/models/__init__.py
odoo/addons/fastapi_auth_partner/models/auth_directory.py
odoo/addons/fastapi_auth_partner/models/auth_partner.py
odoo/addons/fastapi_auth_partner/models/fastapi_endpoint.py
odoo/addons/fastapi_auth_partner/readme/CONTRIBUTORS.rst
odoo/addons/fastapi_auth_partner/readme/DESCRIPTION.rst
odoo/addons/fastapi_auth_partner/readme/USAGE.rst
odoo/addons/fastapi_auth_partner/routers/__init__.py
odoo/addons/fastapi_auth_partner/routers/auth.py
odoo/addons/fastapi_auth_partner/security/ir.model.access.csv
odoo/addons/fastapi_auth_partner/security/res_group.xml
odoo/addons/fastapi_auth_partner/static/description/icon.png
odoo/addons/fastapi_auth_partner/static/description/index.html
odoo/addons/fastapi_auth_partner/tests/__init__.py
odoo/addons/fastapi_auth_partner/tests/test_auth.py
odoo/addons/fastapi_auth_partner/tests/test_fastapi_auth_partner_demo.py
odoo/addons/fastapi_auth_partner/views/auth_directory_view.xml
odoo/addons/fastapi_auth_partner/views/auth_partner_view.xml
odoo/addons/fastapi_auth_partner/views/fastapi_endpoint_view.xml
odoo/addons/fastapi_auth_partner/wizards/__init__.py
odoo/addons/fastapi_auth_partner/wizards/wizard_auth_partner_impersonate.py
odoo/addons/fastapi_auth_partner/wizards/wizard_auth_partner_impersonate_view.xml
odoo/addons/fastapi_auth_partner/wizards/wizard_auth_partner_reset_password.py
odoo/addons/fastapi_auth_partner/wizards/wizard_auth_partner_reset_password_view.xml
odoo_addon_fastapi_auth_partner-16.0.1.0.0.4.dist-info/METADATA
odoo_addon_fastapi_auth_partner-16.0.1.0.0.4.dist-info/WHEEL
odoo_addon_fastapi_auth_partner-16.0.1.0.0.4.dist-info/top_level.txt
odoo_addon_fastapi_auth_partner-16.0.1.0.0.4.dist-info/RECORD
